django_erd_generator/.flake8
django_erd_generator/__init__.py
django_erd_generator/apps.py
django_erd_generator/contrib/__init__.py
django_erd_generator/contrib/dialects.py
django_erd_generator/contrib/gis_fields.py
django_erd_generator/contrib/markdown.py
django_erd_generator/definitions/__init__.py
django_erd_generator/definitions/base.py
django_erd_generator/definitions/fields.py
django_erd_generator/definitions/models.py
django_erd_generator/definitions/relationships.py
django_erd_generator/management/__init__.py
django_erd_generator/management/commands/__init__.py
django_erd_generator/management/commands/generate_data_dictionary.py
django_erd_generator/management/commands/generate_erd.py
django_erd_generator/utils/__init__.py
django_erd_generator/utils/data_dictionary.py
django_erd_generator/utils/git.py
django_erd_generator-0.1.6.dist-info/METADATA
django_erd_generator-0.1.6.dist-info/WHEEL
django_erd_generator-0.1.6.dist-info/licenses/LICENSE
django_erd_generator-0.1.6.dist-info/RECORD
