Metadata-Version: 2.4
Name: django-erd-generator
Version: 0.1.6
Summary: CLI tool to generate ER diagrams from Django models for Mermaid.js, PlantUML, and dbdiagram.io
Project-URL: Homepage, https://github.com/marzukia/django-erd
Project-URL: Documentation, https://github.com/marzukia/django-erd#readme
Project-URL: Source, https://github.com/marzukia/django-erd
Project-URL: Issue Tracker, https://github.com/marzukia/django-erd/issues
Author-email: Andryo Marzuki <andryo@mrzk.io>
License-Expression: MIT
License-File: LICENSE
Keywords: ER diagram,ERD,PlantUML,data dictionary,dbdiagram,django,entity relationship,markdown,mermaid,model documentation,schema documentation,visualization
Classifier: Development Status :: 4 - Beta
Classifier: Environment :: Console
Classifier: Framework :: Django
Classifier: Intended Audience :: Developers
Classifier: License :: OSI Approved :: MIT License
Classifier: Programming Language :: Python
Classifier: Programming Language :: Python :: 3
Classifier: Programming Language :: Python :: 3.8
Classifier: Topic :: Database
Classifier: Topic :: Documentation :: Sphinx
Classifier: Topic :: Software Development :: Code Generators
Classifier: Topic :: Software Development :: Documentation
Classifier: Topic :: Text Processing :: Markup :: Markdown
Requires-Python: >=3.8
